optwps/__init__.py
optwps/optwps.py
optwps/utils.py
optwps-1.1.0.dist-info/METADATA
optwps-1.1.0.dist-info/WHEEL
optwps-1.1.0.dist-info/entry_points.txt
optwps-1.1.0.dist-info/licenses/LICENSE
optwps-1.1.0.dist-info/RECORD
