Metadata-Version: 2.4
Name: optwps
Version: 1.1.0
Summary: Fast Window Protection Score calculator for cell-free DNA analysis
Project-URL: Documentation, https://github.com/VasLem/optwps/README.md
Project-URL: Repository, https://github.com/VasLem/optwps
Project-URL: Bug Tracker, https://github.com/VasLem/optwps/issues
Author-email: Vasileios Lemonidis <vaslemonidis@hotmail.com>
Maintainer-email: Vasileios Lemonidis <vaslemonidis@hotmail.com>
License: BSD
License-File: LICENSE
Keywords: BAM,WPS,bioinformatics,cell-free-DNA,cfDNA,genomics,nucleosome,sequencing
Classifier: Development Status :: 4 - Beta
Classifier: Intended Audience :: Science/Research
Classifier: License :: OSI Approved :: BSD License
Classifier: Operating System :: OS Independent
Classifier: Programming Language :: Python :: 3
Classifier: Programming Language :: Python :: 3.7
Classifier: Programming Language :: Python :: 3.8
Classifier: Programming Language :: Python :: 3.9
Classifier: Programming Language :: Python :: 3.10
Classifier: Programming Language :: Python :: 3.11
Classifier: Topic :: Scientific/Engineering :: Bio-Informatics
Requires-Python: >=3.7
Requires-Dist: bx-python
Requires-Dist: pandas
Requires-Dist: pigz
Requires-Dist: pysam
Requires-Dist: tqdm
Provides-Extra: dev
Requires-Dist: black; extra == 'dev'
Requires-Dist: flake8; extra == 'dev'
Requires-Dist: isort; extra == 'dev'
Requires-Dist: mypy; extra == 'dev'
Requires-Dist: pytest-cov; extra == 'dev'
Requires-Dist: pytest>=6.0; extra == 'dev'
Provides-Extra: test
Requires-Dist: pytest-cov; extra == 'test'
Requires-Dist: pytest>=6.0; extra == 'test'
